dgs_py-1.0.2.dist-info/RECORD
dgs_py-1.0.2.dist-info/WHEEL
dgs_py-1.0.2.dist-info/top_level.txt
dgs_py-1.0.2.dist-info/METADATA
dgs/__init__.py
dgs/_C.cpython-313-darwin.so
