Metadata-Version: 2.4
Name: dgs-py
Version: 1.0.2
Summary: Dynamic Gaussian Splats
Author-email: Daniel Elwell <de@true3d.com>
License-Expression: MIT
Project-URL: Homepage, https://github.com/splatsdotcom/DGS
Project-URL: Repository, https://github.com/splatsdotcom/DGS
Project-URL: Issues, https://github.com/splatsdotcom/DGS/issues
Classifier: Intended Audience :: Developers
Classifier: Operating System :: OS Independent
Classifier: Programming Language :: Python :: 3
Classifier: Programming Language :: Python :: 3.9
Classifier: Programming Language :: Python :: 3.10
Classifier: Programming Language :: Python :: 3.11
Classifier: Programming Language :: Python :: 3.12
Classifier: Programming Language :: Python :: 3.13
Requires-Python: >=3.9
